dummy_text_generator/__init__.py
dummy_text_generator/actions.py
dummy_text_generator/comments.py
dummy_text_generator/details.py
dummy_text_generator/hashtags.py
dummy_text_generator/mail_domains.py
dummy_text_generator/names.py
dummy_text_generator/starts.py
dummy_text_generator/topics.py
dummy_text_generator-0.1.0.dist-info/LICENSE
dummy_text_generator-0.1.0.dist-info/METADATA
dummy_text_generator-0.1.0.dist-info/WHEEL
dummy_text_generator-0.1.0.dist-info/top_level.txt
dummy_text_generator-0.1.0.dist-info/RECORD
