Metadata-Version: 2.2
Name: dummy-text-generator
Version: 0.1.0
Summary: A Python library for generating random texts, sentences, paragraphs, comments, and names in multiple languages like English, Spanish, French, and German.
Author-email: Dairo Mosquera <dairoandres115@outlook.com>
Project-URL: Homepage, https://github.com/daireto/dummy-text-generator
Project-URL: Issues, https://github.com/daireto/dummy-text-generator/issues
Project-URL: Repository, https://github.com/daireto/dummy-text-generator
Keywords: dummy-text-generator,dummy-text,text-generator,dummy,generator
Classifier: Programming Language :: Python :: 3.10
Classifier: Programming Language :: Python :: 3.11
Classifier: Programming Language :: Python :: 3.12
Classifier: Programming Language :: Python :: 3.13
Classifier: Programming Language :: Python :: 3.14
Classifier: License :: OSI Approved :: MIT License
Classifier: Operating System :: OS Independent
Classifier: Intended Audience :: Developers
Requires-Python: >=3.10
License-File: LICENSE
